ucheck/__init__.py
ucheck/config.yaml
ucheck/exceptions.py
ucheck/ucheck.py
ucheck-0.0.6.dist-info/LICENSE
ucheck-0.0.6.dist-info/WHEEL
ucheck-0.0.6.dist-info/METADATA
ucheck-0.0.6.dist-info/RECORD
