Metadata-Version: 2.1
Name: ucheck
Version: 0.0.6
Summary: ucheck library
Home-page: https://github.com/irahorecka/ucheck
Author: Ira Horecka
Author-email: ira89@icloud.com
Requires-Python: >=3.6
Classifier: Intended Audience :: Developers
Classifier: License :: OSI Approved :: MIT License
Classifier: Operating System :: OS Independent
Classifier: Programming Language :: Python :: 3.6
Classifier: Programming Language :: Python :: 3.7
Classifier: Programming Language :: Python :: 3.8
Classifier: Programming Language :: Python :: 3.9
Classifier: Programming Language :: Python :: 3.10
Classifier: Topic :: Software Development :: Libraries
Classifier: Topic :: Utilities
Requires-Dist: selenium>=4.0.0
Requires-Dist: PyYAML>=6.0
